{"generated_at":"2026-03-06T17:35:40.178959","generated_at_human":"March 06, 2026 at 05:35 PM","pipeline":{"station_count":148,"stations_with_forecast":148,"stations_missing":[],"data_freshness":"2026-03-06T17:35:37.721388"},"snow_alerts":[{"station_id":"mount_baker_wa","name":"Mount Baker, WA","region":"Pacific Northwest","snow_score":95,"snowfall_7d_cm":56.2,"snowfall_3d_cm":13.6,"peak_day":"2026-03-11","peak_day_cm":17.8,"temp_range":"-12 to 4\u00b0C","alert_level":"HIGH"},{"station_id":"stevens_pass_wa","name":"Stevens Pass, WA","region":"Pacific Northwest","snow_score":89,"snowfall_7d_cm":46.1,"snowfall_3d_cm":13.9,"peak_day":"2026-03-11","peak_day_cm":13.9,"temp_range":"-9 to 4\u00b0C","alert_level":"HIGH"},{"station_id":"crystal_mountain_wa","name":"Crystal Mountain, WA","region":"us_pacific_ski","snow_score":87,"snowfall_7d_cm":25.0,"snowfall_3d_cm":4.1,"peak_day":"2026-03-11","peak_day_cm":8.1,"temp_range":"-11 to 4\u00b0C","alert_level":"HIGH"},{"station_id":"snoqualmie_pass_wa","name":"Snoqualmie Pass, WA","region":"us_pacific_ski","snow_score":86,"snowfall_7d_cm":41.7,"snowfall_3d_cm":2.0,"peak_day":"2026-03-11","peak_day_cm":16.4,"temp_range":"-4 to 6\u00b0C","alert_level":"HIGH"},{"station_id":"magadan_russia","name":"Magadan, Russia","region":"Eastern Siberia","snow_score":83,"snowfall_7d_cm":20.1,"snowfall_3d_cm":1.7,"peak_day":"2026-03-09","peak_day_cm":13.2,"temp_range":"-14 to -1\u00b0C","alert_level":"HIGH"},{"station_id":"murmansk_russia","name":"Murmansk, Russia","region":"Arctic Russia","snow_score":81,"snowfall_7d_cm":24.0,"snowfall_3d_cm":16.4,"peak_day":"2026-03-07","peak_day_cm":8.1,"temp_range":"-14 to 1\u00b0C","alert_level":"HIGH"},{"station_id":"whistler_bc","name":"Whistler, BC","region":"Western Canada","snow_score":77,"snowfall_7d_cm":24.9,"snowfall_3d_cm":1.6,"peak_day":"2026-03-11","peak_day_cm":14.2,"temp_range":"-10 to 8\u00b0C","alert_level":"HIGH"},{"station_id":"sept_iles_qc","name":"Sept-Iles, QC","region":"Eastern Canada","snow_score":73,"snowfall_7d_cm":16.4,"snowfall_3d_cm":0.8,"peak_day":"2026-03-12","peak_day_cm":11.9,"temp_range":"-15 to 4\u00b0C","alert_level":"HIGH"},{"station_id":"mount_hood_or","name":"Mount Hood, OR","region":"Pacific Northwest","snow_score":72,"snowfall_7d_cm":14.5,"snowfall_3d_cm":0.1,"peak_day":"2026-03-10","peak_day_cm":8.8,"temp_range":"-11 to 7\u00b0C","alert_level":"HIGH"},{"station_id":"quebec_city_qc","name":"Quebec City, QC","region":"Eastern Canada","snow_score":70,"snowfall_7d_cm":16.9,"snowfall_3d_cm":0.1,"peak_day":"2026-03-11","peak_day_cm":11.3,"temp_range":"-11 to 8\u00b0C","alert_level":"HIGH"},{"station_id":"mont_sainte_anne_qc","name":"Mont-Sainte-Anne, QC","region":"canada_east_ski","snow_score":69,"snowfall_7d_cm":16.1,"snowfall_3d_cm":0.9,"peak_day":"2026-03-11","peak_day_cm":11.0,"temp_range":"-13 to 8\u00b0C","alert_level":"HIGH"},{"station_id":"le_massif_qc","name":"Le Massif, QC","region":"canada_east_ski","snow_score":68,"snowfall_7d_cm":15.7,"snowfall_3d_cm":0.5,"peak_day":"2026-03-11","peak_day_cm":10.8,"temp_range":"-19 to 7\u00b0C","alert_level":"HIGH"},{"station_id":"revelstoke_bc","name":"Revelstoke, BC","region":"Western Canada","snow_score":65,"snowfall_7d_cm":15.2,"snowfall_3d_cm":2.9,"peak_day":"2026-03-11","peak_day_cm":4.5,"temp_range":"-13 to 10\u00b0C","alert_level":"HIGH"},{"station_id":"astana_kazakhstan","name":"Astana, Kazakhstan","region":"Central Asia","snow_score":65,"snowfall_7d_cm":9.3,"snowfall_3d_cm":3.5,"peak_day":"2026-03-12","peak_day_cm":2.7,"temp_range":"-26 to 1\u00b0C","alert_level":"HIGH"},{"station_id":"marmot_basin_ab","name":"Marmot Basin, AB","region":"canada_ab_ski","snow_score":64,"snowfall_7d_cm":12.0,"snowfall_3d_cm":0.3,"peak_day":"2026-03-12","peak_day_cm":9.9,"temp_range":"-16 to 4\u00b0C","alert_level":"HIGH"},{"station_id":"lake_louise_ab","name":"Lake Louise, AB","region":"Canadian Rockies","snow_score":62,"snowfall_7d_cm":8.7,"snowfall_3d_cm":3.5,"peak_day":"2026-03-08","peak_day_cm":3.5,"temp_range":"-20 to 5\u00b0C","alert_level":"HIGH"},{"station_id":"nakiska_ab","name":"Nakiska, AB","region":"canada_ab_ski","snow_score":62,"snowfall_7d_cm":8.8,"snowfall_3d_cm":3.0,"peak_day":"2026-03-08","peak_day_cm":3.0,"temp_range":"-14 to 8\u00b0C","alert_level":"HIGH"},{"station_id":"ifrane_morocco","name":"Ifrane, Morocco","region":"African Mountains","snow_score":61,"snowfall_7d_cm":22.0,"snowfall_3d_cm":0.0,"peak_day":"2026-03-10","peak_day_cm":16.0,"temp_range":"-2 to 10\u00b0C","alert_level":"HIGH"},{"station_id":"burlington_vt","name":"Burlington, VT","region":"Appalachian / Eastern US","snow_score":61,"snowfall_7d_cm":13.0,"snowfall_3d_cm":0.0,"peak_day":"2026-03-12","peak_day_cm":8.3,"temp_range":"-8 to 13\u00b0C","alert_level":"HIGH"},{"station_id":"tomsk_russia","name":"Tomsk, Russia","region":"Western Siberia","snow_score":60,"snowfall_7d_cm":6.9,"snowfall_3d_cm":3.9,"peak_day":"2026-03-12","peak_day_cm":2.5,"temp_range":"-23 to 1\u00b0C","alert_level":"HIGH"},{"station_id":"spirit_mountain_mn","name":"Spirit Mountain, MN","region":"us_midwest_ski","snow_score":60,"snowfall_7d_cm":12.4,"snowfall_3d_cm":2.6,"peak_day":"2026-03-10","peak_day_cm":5.5,"temp_range":"-14 to 9\u00b0C","alert_level":"HIGH"},{"station_id":"midelt_morocco","name":"Midelt, Morocco","region":"African Mountains","snow_score":59,"snowfall_7d_cm":19.4,"snowfall_3d_cm":0.0,"peak_day":"2026-03-11","peak_day_cm":12.6,"temp_range":"-0 to 14\u00b0C","alert_level":"MODERATE"},{"station_id":"novosibirsk_russia","name":"Novosibirsk, Russia","region":"Western Siberia","snow_score":58,"snowfall_7d_cm":7.5,"snowfall_3d_cm":3.9,"peak_day":"2026-03-12","peak_day_cm":2.7,"temp_range":"-24 to 1\u00b0C","alert_level":"MODERATE"},{"station_id":"banff_ab","name":"Banff, AB","region":"Canadian Rockies","snow_score":57,"snowfall_7d_cm":6.9,"snowfall_3d_cm":2.0,"peak_day":"2026-03-12","peak_day_cm":2.6,"temp_range":"-12 to 9\u00b0C","alert_level":"MODERATE"},{"station_id":"gore_mountain_ny","name":"Gore Mountain, NY","region":"us_northeast_ski","snow_score":57,"snowfall_7d_cm":10.0,"snowfall_3d_cm":4.6,"peak_day":"2026-03-12","peak_day_cm":5.4,"temp_range":"-7 to 12\u00b0C","alert_level":"MODERATE"},{"station_id":"duluth_mn","name":"Duluth, MN","region":"Lake Superior Snow Belt","snow_score":56,"snowfall_7d_cm":11.0,"snowfall_3d_cm":2.5,"peak_day":"2026-03-11","peak_day_cm":4.5,"temp_range":"-11 to 9\u00b0C","alert_level":"MODERATE"},{"station_id":"urumqi_china","name":"Urumqi, China","region":"Northwest China","snow_score":56,"snowfall_7d_cm":8.4,"snowfall_3d_cm":0.0,"peak_day":"2026-03-11","peak_day_cm":6.8,"temp_range":"-18 to 9\u00b0C","alert_level":"MODERATE"},{"station_id":"big_white_bc","name":"Big White, BC","region":"canada_bc_ski","snow_score":56,"snowfall_7d_cm":6.0,"snowfall_3d_cm":3.9,"peak_day":"2026-03-07","peak_day_cm":2.6,"temp_range":"-15 to 3\u00b0C","alert_level":"MODERATE"},{"station_id":"ironwood_mi","name":"Ironwood, MI","region":"Lake Superior Snow Belt","snow_score":55,"snowfall_7d_cm":10.6,"snowfall_3d_cm":2.4,"peak_day":"2026-03-10","peak_day_cm":4.9,"temp_range":"-11 to 8\u00b0C","alert_level":"MODERATE"},{"station_id":"winter_park_co","name":"Winter Park, CO","region":"us_rockies_co_expanded","snow_score":55,"snowfall_7d_cm":9.6,"snowfall_3d_cm":9.6,"peak_day":"2026-03-06","peak_day_cm":6.7,"temp_range":"-12 to 7\u00b0C","alert_level":"MODERATE"},{"station_id":"kicking_horse_bc","name":"Kicking Horse, BC","region":"canada_bc_ski","snow_score":55,"snowfall_7d_cm":8.6,"snowfall_3d_cm":2.1,"peak_day":"2026-03-12","peak_day_cm":3.6,"temp_range":"-10 to 10\u00b0C","alert_level":"MODERATE"},{"station_id":"blue_mountain_on","name":"Blue Mountain, ON","region":"canada_east_ski","snow_score":55,"snowfall_7d_cm":9.9,"snowfall_3d_cm":0.0,"peak_day":"2026-03-11","peak_day_cm":7.3,"temp_range":"-9 to 16\u00b0C","alert_level":"MODERATE"},{"station_id":"ashland_wi","name":"Ashland, WI","region":"Lake Superior Snow Belt","snow_score":54,"snowfall_7d_cm":11.9,"snowfall_3d_cm":1.9,"peak_day":"2026-03-10","peak_day_cm":5.2,"temp_range":"-13 to 10\u00b0C","alert_level":"MODERATE"},{"station_id":"omsk_russia","name":"Omsk, Russia","region":"Western Siberia","snow_score":54,"snowfall_7d_cm":6.2,"snowfall_3d_cm":3.7,"peak_day":"2026-03-08","peak_day_cm":2.5,"temp_range":"-27 to -1\u00b0C","alert_level":"MODERATE"},{"station_id":"whiteface_ny","name":"Whiteface, NY","region":"us_northeast_ski","snow_score":54,"snowfall_7d_cm":7.6,"snowfall_3d_cm":0.0,"peak_day":"2026-03-12","peak_day_cm":5.9,"temp_range":"-14 to 6\u00b0C","alert_level":"MODERATE"},{"station_id":"stowe_vt","name":"Stowe, VT","region":"us_northeast_ski","snow_score":53,"snowfall_7d_cm":7.4,"snowfall_3d_cm":1.0,"peak_day":"2026-03-12","peak_day_cm":6.4,"temp_range":"-9 to 10\u00b0C","alert_level":"MODERATE"},{"station_id":"marquette_mi","name":"Marquette, MI","region":"Lake Superior Snow Belt","snow_score":51,"snowfall_7d_cm":9.7,"snowfall_3d_cm":2.8,"peak_day":"2026-03-11","peak_day_cm":4.2,"temp_range":"-7 to 8\u00b0C","alert_level":"MODERATE"},{"station_id":"breckenridge_co","name":"Breckenridge, CO","region":"Colorado Rockies","snow_score":51,"snowfall_7d_cm":7.5,"snowfall_3d_cm":7.5,"peak_day":"2026-03-06","peak_day_cm":4.4,"temp_range":"-13 to 7\u00b0C","alert_level":"MODERATE"},{"station_id":"bridger_bowl_mt","name":"Bridger Bowl, MT","region":"us_rockies_north","snow_score":51,"snowfall_7d_cm":8.5,"snowfall_3d_cm":2.5,"peak_day":"2026-03-10","peak_day_cm":5.6,"temp_range":"-11 to 7\u00b0C","alert_level":"MODERATE"},{"station_id":"sun_peaks_bc","name":"Sun Peaks, BC","region":"canada_bc_ski","snow_score":51,"snowfall_7d_cm":4.7,"snowfall_3d_cm":0.5,"peak_day":"2026-03-11","peak_day_cm":2.2,"temp_range":"-10 to 7\u00b0C","alert_level":"MODERATE"},{"station_id":"red_mountain_bc","name":"Red Mountain, BC","region":"canada_bc_ski","snow_score":51,"snowfall_7d_cm":4.5,"snowfall_3d_cm":2.7,"peak_day":"2026-03-07","peak_day_cm":2.7,"temp_range":"-11 to 6\u00b0C","alert_level":"MODERATE"},{"station_id":"jay_peak_vt","name":"Jay Peak, VT","region":"us_northeast_ski","snow_score":50,"snowfall_7d_cm":7.2,"snowfall_3d_cm":0.0,"peak_day":"2026-03-12","peak_day_cm":6.9,"temp_range":"-10 to 10\u00b0C","alert_level":"MODERATE"},{"station_id":"fernie_bc","name":"Fernie, BC","region":"canada_bc_ski","snow_score":50,"snowfall_7d_cm":5.9,"snowfall_3d_cm":0.3,"peak_day":"2026-03-12","peak_day_cm":3.1,"temp_range":"-11 to 12\u00b0C","alert_level":"MODERATE"},{"station_id":"killington_vt","name":"Killington, VT","region":"us_northeast_ski","snow_score":48,"snowfall_7d_cm":4.9,"snowfall_3d_cm":3.5,"peak_day":"2026-03-06","peak_day_cm":3.5,"temp_range":"-12 to 7\u00b0C","alert_level":"MODERATE"},{"station_id":"tremblant_qc","name":"Tremblant, QC","region":"canada_east_ski","snow_score":48,"snowfall_7d_cm":5.6,"snowfall_3d_cm":0.0,"peak_day":"2026-03-11","peak_day_cm":3.5,"temp_range":"-8 to 8\u00b0C","alert_level":"MODERATE"},{"station_id":"smugglers_notch_vt","name":"Smugglers' Notch, VT","region":"us_northeast_ski","snow_score":46,"snowfall_7d_cm":6.4,"snowfall_3d_cm":0.0,"peak_day":"2026-03-12","peak_day_cm":6.4,"temp_range":"-8 to 14\u00b0C","alert_level":"MODERATE"},{"station_id":"sugarloaf_me","name":"Sugarloaf, ME","region":"us_northeast_ski","snow_score":46,"snowfall_7d_cm":5.4,"snowfall_3d_cm":0.0,"peak_day":"2026-03-11","peak_day_cm":3.4,"temp_range":"-15 to 6\u00b0C","alert_level":"MODERATE"},{"station_id":"hakuba_japan","name":"Hakuba, Japan","region":"Japan Mountains","snow_score":45,"snowfall_7d_cm":7.0,"snowfall_3d_cm":1.1,"peak_day":"2026-03-10","peak_day_cm":3.5,"temp_range":"-8 to 13\u00b0C","alert_level":"MODERATE"},{"station_id":"monarch_co","name":"Monarch, CO","region":"us_rockies_co_expanded","snow_score":45,"snowfall_7d_cm":6.9,"snowfall_3d_cm":6.9,"peak_day":"2026-03-07","peak_day_cm":5.7,"temp_range":"-15 to 5\u00b0C","alert_level":"MODERATE"},{"station_id":"land_o_lakes_wi","name":"Land O'Lakes, WI","region":"Northern Wisconsin","snow_score":44,"snowfall_7d_cm":5.9,"snowfall_3d_cm":1.5,"peak_day":"2026-03-10","peak_day_cm":2.9,"temp_range":"-9 to 8\u00b0C","alert_level":"MODERATE"},{"station_id":"tromso_norway","name":"Troms\u00f8, Norway","region":"Scandinavia","snow_score":44,"snowfall_7d_cm":10.2,"snowfall_3d_cm":0.0,"peak_day":"2026-03-11","peak_day_cm":4.3,"temp_range":"-1 to 6\u00b0C","alert_level":"MODERATE"},{"station_id":"okemo_vt","name":"Okemo, VT","region":"us_northeast_ski","snow_score":44,"snowfall_7d_cm":5.1,"snowfall_3d_cm":3.8,"peak_day":"2026-03-06","peak_day_cm":3.8,"temp_range":"-6 to 12\u00b0C","alert_level":"MODERATE"},{"station_id":"hancock_mi","name":"Hancock, MI","region":"Lake Superior Snow Belt","snow_score":43,"snowfall_7d_cm":5.7,"snowfall_3d_cm":2.7,"peak_day":"2026-03-07","peak_day_cm":2.7,"temp_range":"-9 to 7\u00b0C","alert_level":"MODERATE"},{"station_id":"phelps_wi","name":"Phelps, WI","region":"Northern Wisconsin","snow_score":42,"snowfall_7d_cm":5.4,"snowfall_3d_cm":0.6,"peak_day":"2026-03-10","peak_day_cm":2.8,"temp_range":"-10 to 8\u00b0C","alert_level":"MODERATE"},{"station_id":"bishkek_kyrgyzstan","name":"Bishkek, Kyrgyzstan","region":"Central Asia","snow_score":42,"snowfall_7d_cm":4.2,"snowfall_3d_cm":0.0,"peak_day":"2026-03-10","peak_day_cm":2.7,"temp_range":"-7 to 16\u00b0C","alert_level":"MODERATE"},{"station_id":"panorama_bc","name":"Panorama, BC","region":"canada_bc_ski","snow_score":42,"snowfall_7d_cm":3.5,"snowfall_3d_cm":0.5,"peak_day":"2026-03-09","peak_day_cm":1.2,"temp_range":"-7 to 10\u00b0C","alert_level":"MODERATE"},{"station_id":"krasnoyarsk_russia","name":"Krasnoyarsk, Russia","region":"Central Siberia","snow_score":41,"snowfall_7d_cm":4.3,"snowfall_3d_cm":3.2,"peak_day":"2026-03-06","peak_day_cm":1.3,"temp_range":"-21 to 6\u00b0C","alert_level":"MODERATE"},{"station_id":"churchill_mb","name":"Churchill, MB","region":"Northern Canada","snow_score":41,"snowfall_7d_cm":2.9,"snowfall_3d_cm":2.7,"peak_day":"2026-03-06","peak_day_cm":2.4,"temp_range":"-30 to -14\u00b0C","alert_level":"MODERATE"},{"station_id":"houghton_mi","name":"Houghton, MI (Keweenaw)","region":"Lake Superior Snow Belt","snow_score":40,"snowfall_7d_cm":5.0,"snowfall_3d_cm":2.0,"peak_day":"2026-03-10","peak_day_cm":2.2,"temp_range":"-9 to 8\u00b0C","alert_level":"MODERATE"},{"station_id":"loon_mountain_nh","name":"Loon Mountain, NH","region":"us_northeast_ski","snow_score":40,"snowfall_7d_cm":2.9,"snowfall_3d_cm":1.6,"peak_day":"2026-03-06","peak_day_cm":1.6,"temp_range":"-10 to 7\u00b0C","alert_level":"MODERATE"},{"station_id":"asahikawa_japan","name":"Asahikawa, Japan","region":"Northern Japan","snow_score":39,"snowfall_7d_cm":5.0,"snowfall_3d_cm":4.8,"peak_day":"2026-03-06","peak_day_cm":2.4,"temp_range":"-8 to 5\u00b0C","alert_level":"MODERATE"},{"station_id":"big_sky_mt","name":"Big Sky, MT","region":"us_rockies_north","snow_score":39,"snowfall_7d_cm":4.2,"snowfall_3d_cm":2.1,"peak_day":"2026-03-10","peak_day_cm":2.1,"temp_range":"-10 to 4\u00b0C","alert_level":"MODERATE"},{"station_id":"schweitzer_id","name":"Schweitzer, ID","region":"us_rockies_north","snow_score":39,"snowfall_7d_cm":3.6,"snowfall_3d_cm":3.1,"peak_day":"2026-03-07","peak_day_cm":3.1,"temp_range":"-9 to 8\u00b0C","alert_level":"MODERATE"},{"station_id":"sunday_river_me","name":"Sunday River, ME","region":"us_northeast_ski","snow_score":39,"snowfall_7d_cm":4.7,"snowfall_3d_cm":0.0,"peak_day":"2026-03-11","peak_day_cm":3.4,"temp_range":"-7 to 10\u00b0C","alert_level":"MODERATE"},{"station_id":"almaty_kazakhstan","name":"Almaty, Kazakhstan","region":"Central Asia","snow_score":38,"snowfall_7d_cm":3.7,"snowfall_3d_cm":0.6,"peak_day":"2026-03-11","peak_day_cm":1.8,"temp_range":"-15 to 14\u00b0C","alert_level":"MODERATE"},{"station_id":"mount_washington_nh","name":"Mount Washington, NH","region":"Appalachian / Eastern US","snow_score":38,"snowfall_7d_cm":2.5,"snowfall_3d_cm":0.6,"peak_day":"2026-03-12","peak_day_cm":1.1,"temp_range":"-16 to 4\u00b0C","alert_level":"MODERATE"},{"station_id":"irkutsk_russia","name":"Irkutsk, Russia","region":"Central Siberia","snow_score":36,"snowfall_7d_cm":3.2,"snowfall_3d_cm":0.0,"peak_day":"2026-03-11","peak_day_cm":3.1,"temp_range":"-20 to 7\u00b0C","alert_level":"MODERATE"},{"station_id":"sapporo_japan","name":"Sapporo, Japan","region":"Northern Japan","snow_score":36,"snowfall_7d_cm":3.4,"snowfall_3d_cm":3.4,"peak_day":"2026-03-06","peak_day_cm":2.5,"temp_range":"-7 to 4\u00b0C","alert_level":"MODERATE"},{"station_id":"alta_ut","name":"Alta/Snowbird, UT","region":"us_rockies_utah","snow_score":36,"snowfall_7d_cm":4.5,"snowfall_3d_cm":4.5,"peak_day":"2026-03-06","peak_day_cm":4.5,"temp_range":"-11 to 8\u00b0C","alert_level":"MODERATE"},{"station_id":"cannon_mountain_nh","name":"Cannon Mountain, NH","region":"us_northeast_ski","snow_score":36,"snowfall_7d_cm":2.6,"snowfall_3d_cm":1.3,"peak_day":"2026-03-06","peak_day_cm":1.3,"temp_range":"-12 to 6\u00b0C","alert_level":"MODERATE"},{"station_id":"winnipeg_mb","name":"Winnipeg, MB","region":"Great Lakes Regional","snow_score":35,"snowfall_7d_cm":2.7,"snowfall_3d_cm":0.3,"peak_day":"2026-03-11","peak_day_cm":1.4,"temp_range":"-16 to 5\u00b0C","alert_level":"MODERATE"},{"station_id":"lutsen_mn","name":"Lutsen, MN","region":"us_midwest_ski","snow_score":34,"snowfall_7d_cm":2.7,"snowfall_3d_cm":2.1,"peak_day":"2026-03-07","peak_day_cm":2.1,"temp_range":"-10 to 7\u00b0C","alert_level":"MODERATE"},{"station_id":"ski_cooper_co","name":"Ski Cooper, CO","region":"us_rockies_co_expanded","snow_score":33,"snowfall_7d_cm":2.9,"snowfall_3d_cm":2.9,"peak_day":"2026-03-07","peak_day_cm":1.6,"temp_range":"-15 to 5\u00b0C","alert_level":"MODERATE"},{"station_id":"kamchatka_russia","name":"Kamchatka, Russia","region":"Eastern Siberia","snow_score":32,"snowfall_7d_cm":2.0,"snowfall_3d_cm":0.6,"peak_day":"2026-03-11","peak_day_cm":1.4,"temp_range":"-8 to 4\u00b0C","alert_level":"MODERATE"},{"station_id":"iron_mountain_mi","name":"Iron Mountain, MI","region":"Great Lakes Regional","snow_score":31,"snowfall_7d_cm":2.6,"snowfall_3d_cm":0.0,"peak_day":"2026-03-11","peak_day_cm":1.7,"temp_range":"-9 to 11\u00b0C","alert_level":"MODERATE"},{"station_id":"grand_targhee_wy","name":"Grand Targhee, WY","region":"us_rockies_north","snow_score":31,"snowfall_7d_cm":1.6,"snowfall_3d_cm":1.3,"peak_day":"2026-03-06","peak_day_cm":1.1,"temp_range":"-12 to 3\u00b0C","alert_level":"MODERATE"},{"station_id":"eagle_river_wi","name":"Eagle River, WI","region":"Northern Wisconsin","snow_score":30,"snowfall_7d_cm":2.8,"snowfall_3d_cm":0.3,"peak_day":"2026-03-10","peak_day_cm":1.6,"temp_range":"-8 to 9\u00b0C","alert_level":"MODERATE"},{"station_id":"aspen_co","name":"Aspen, CO","region":"Colorado Rockies","snow_score":30,"snowfall_7d_cm":5.0,"snowfall_3d_cm":5.0,"peak_day":"2026-03-06","peak_day_cm":3.5,"temp_range":"-8 to 10\u00b0C","alert_level":"MODERATE"},{"station_id":"syracuse_ny","name":"Syracuse, NY","region":"Appalachian / Eastern US","snow_score":30,"snowfall_7d_cm":2.2,"snowfall_3d_cm":0.0,"peak_day":"2026-03-12","peak_day_cm":2.2,"temp_range":"-3 to 20\u00b0C","alert_level":"MODERATE"}],"top_10_stations":[{"station_id":"mount_baker_wa","name":"Mount Baker, WA","region":"Pacific Northwest","snow_score":95,"snowfall_7d_cm":56.2,"snowfall_3d_cm":13.6,"peak_day":"2026-03-11","peak_day_cm":17.8,"temp_range":"-12 to 4\u00b0C","alert_level":"HIGH"},{"station_id":"stevens_pass_wa","name":"Stevens Pass, WA","region":"Pacific Northwest","snow_score":89,"snowfall_7d_cm":46.1,"snowfall_3d_cm":13.9,"peak_day":"2026-03-11","peak_day_cm":13.9,"temp_range":"-9 to 4\u00b0C","alert_level":"HIGH"},{"station_id":"crystal_mountain_wa","name":"Crystal Mountain, WA","region":"us_pacific_ski","snow_score":87,"snowfall_7d_cm":25.0,"snowfall_3d_cm":4.1,"peak_day":"2026-03-11","peak_day_cm":8.1,"temp_range":"-11 to 4\u00b0C","alert_level":"HIGH"},{"station_id":"snoqualmie_pass_wa","name":"Snoqualmie Pass, WA","region":"us_pacific_ski","snow_score":86,"snowfall_7d_cm":41.7,"snowfall_3d_cm":2.0,"peak_day":"2026-03-11","peak_day_cm":16.4,"temp_range":"-4 to 6\u00b0C","alert_level":"HIGH"},{"station_id":"magadan_russia","name":"Magadan, Russia","region":"Eastern Siberia","snow_score":83,"snowfall_7d_cm":20.1,"snowfall_3d_cm":1.7,"peak_day":"2026-03-09","peak_day_cm":13.2,"temp_range":"-14 to -1\u00b0C","alert_level":"HIGH"},{"station_id":"murmansk_russia","name":"Murmansk, Russia","region":"Arctic Russia","snow_score":81,"snowfall_7d_cm":24.0,"snowfall_3d_cm":16.4,"peak_day":"2026-03-07","peak_day_cm":8.1,"temp_range":"-14 to 1\u00b0C","alert_level":"HIGH"},{"station_id":"whistler_bc","name":"Whistler, BC","region":"Western Canada","snow_score":77,"snowfall_7d_cm":24.9,"snowfall_3d_cm":1.6,"peak_day":"2026-03-11","peak_day_cm":14.2,"temp_range":"-10 to 8\u00b0C","alert_level":"HIGH"},{"station_id":"sept_iles_qc","name":"Sept-Iles, QC","region":"Eastern Canada","snow_score":73,"snowfall_7d_cm":16.4,"snowfall_3d_cm":0.8,"peak_day":"2026-03-12","peak_day_cm":11.9,"temp_range":"-15 to 4\u00b0C","alert_level":"HIGH"},{"station_id":"mount_hood_or","name":"Mount Hood, OR","region":"Pacific Northwest","snow_score":72,"snowfall_7d_cm":14.5,"snowfall_3d_cm":0.1,"peak_day":"2026-03-10","peak_day_cm":8.8,"temp_range":"-11 to 7\u00b0C","alert_level":"HIGH"},{"station_id":"quebec_city_qc","name":"Quebec City, QC","region":"Eastern Canada","snow_score":70,"snowfall_7d_cm":16.9,"snowfall_3d_cm":0.1,"peak_day":"2026-03-11","peak_day_cm":11.3,"temp_range":"-11 to 8\u00b0C","alert_level":"HIGH"}],"regional_summary":[{"region":"pacific_northwest","display_name":"Pacific Northwest","station_count":3,"avg_score":85,"max_score":95,"top_station":"Mount Baker, WA","total_7d_cm":116.8},{"region":"us_pacific_ski","display_name":"Us Pacific Ski","station_count":5,"avg_score":39,"max_score":87,"top_station":"Crystal Mountain, WA","total_7d_cm":67.1},{"region":"siberia_east","display_name":"Eastern Siberia","station_count":2,"avg_score":58,"max_score":83,"top_station":"Magadan, Russia","total_7d_cm":22.1},{"region":"arctic_russia","display_name":"Arctic Russia","station_count":3,"avg_score":38,"max_score":81,"top_station":"Murmansk, Russia","total_7d_cm":24.1},{"region":"canada_west","display_name":"Western Canada","station_count":2,"avg_score":71,"max_score":77,"top_station":"Whistler, BC","total_7d_cm":40.1},{"region":"canada_east","display_name":"Eastern Canada","station_count":3,"avg_score":49,"max_score":73,"top_station":"Sept-Iles, QC","total_7d_cm":33.3},{"region":"canada_east_ski","display_name":"Canada East Ski","station_count":4,"avg_score":60,"max_score":69,"top_station":"Mont-Sainte-Anne, QC","total_7d_cm":47.3},{"region":"central_asia","display_name":"Central Asia","station_count":5,"avg_score":29,"max_score":65,"top_station":"Astana, Kazakhstan","total_7d_cm":17.2},{"region":"canada_ab_ski","display_name":"Canada Ab Ski","station_count":2,"avg_score":63,"max_score":64,"top_station":"Marmot Basin, AB","total_7d_cm":20.8},{"region":"canada_rockies","display_name":"Canadian Rockies","station_count":2,"avg_score":60,"max_score":62,"top_station":"Lake Louise, AB","total_7d_cm":15.6},{"region":"africa_mountains","display_name":"African Mountains","station_count":4,"avg_score":30,"max_score":61,"top_station":"Ifrane, Morocco","total_7d_cm":41.4},{"region":"appalachian_eastern_us","display_name":"Appalachian / Eastern US","station_count":5,"avg_score":29,"max_score":61,"top_station":"Burlington, VT","total_7d_cm":19.3},{"region":"siberia_west","display_name":"Western Siberia","station_count":3,"avg_score":57,"max_score":60,"top_station":"Tomsk, Russia","total_7d_cm":20.6},{"region":"us_midwest_ski","display_name":"Us Midwest Ski","station_count":3,"avg_score":34,"max_score":60,"top_station":"Spirit Mountain, MN","total_7d_cm":15.4},{"region":"us_northeast_ski","display_name":"Us Northeast Ski","station_count":12,"avg_score":45,"max_score":57,"top_station":"Gore Mountain, NY","total_7d_cm":66.0},{"region":"lake_superior","display_name":"Lake Superior Snow Belt","station_count":7,"avg_score":47,"max_score":56,"top_station":"Duluth, MN","total_7d_cm":55.6},{"region":"china_northwest","display_name":"Northwest China","station_count":2,"avg_score":28,"max_score":56,"top_station":"Urumqi, China","total_7d_cm":8.4},{"region":"canada_bc_ski","display_name":"Canada Bc Ski","station_count":6,"avg_score":51,"max_score":56,"top_station":"Big White, BC","total_7d_cm":33.2},{"region":"us_rockies_co_expanded","display_name":"Us Rockies Co Expanded","station_count":5,"avg_score":30,"max_score":55,"top_station":"Winter Park, CO","total_7d_cm":21.1},{"region":"colorado_rockies","display_name":"Colorado Rockies","station_count":5,"avg_score":26,"max_score":51,"top_station":"Breckenridge, CO","total_7d_cm":18.4},{"region":"us_rockies_north","display_name":"Us Rockies North","station_count":6,"avg_score":28,"max_score":51,"top_station":"Bridger Bowl, MT","total_7d_cm":18.4},{"region":"japan_mountains","display_name":"Japan Mountains","station_count":2,"avg_score":22,"max_score":45,"top_station":"Hakuba, Japan","total_7d_cm":7.0},{"region":"northern_wisconsin","display_name":"Northern Wisconsin","station_count":3,"avg_score":39,"max_score":44,"top_station":"Land O'Lakes, WI","total_7d_cm":14.1},{"region":"scandinavia","display_name":"Scandinavia","station_count":3,"avg_score":26,"max_score":44,"top_station":"Troms\u00f8, Norway","total_7d_cm":12.7},{"region":"siberia_central","display_name":"Central Siberia","station_count":3,"avg_score":34,"max_score":41,"top_station":"Krasnoyarsk, Russia","total_7d_cm":8.4},{"region":"canada_north","display_name":"Northern Canada","station_count":3,"avg_score":25,"max_score":41,"top_station":"Churchill, MB","total_7d_cm":4.1},{"region":"japan_north","display_name":"Northern Japan","station_count":3,"avg_score":31,"max_score":39,"top_station":"Asahikawa, Japan","total_7d_cm":9.4},{"region":"us_rockies_utah","display_name":"Us Rockies Utah","station_count":2,"avg_score":28,"max_score":36,"top_station":"Alta/Snowbird, UT","total_7d_cm":5.7},{"region":"regional","display_name":"Great Lakes Regional","station_count":4,"avg_score":26,"max_score":35,"top_station":"Winnipeg, MB","total_7d_cm":7.0},{"region":"middle_east_mountains","display_name":"Middle East Mountains","station_count":4,"avg_score":11,"max_score":28,"top_station":"Erzurum, Turkey","total_7d_cm":1.9},{"region":"california_ski","display_name":"California Ski","station_count":4,"avg_score":5,"max_score":16,"top_station":"Mount Shasta, CA","total_7d_cm":0.0},{"region":"china_northeast","display_name":"Northeast China","station_count":3,"avg_score":6,"max_score":10,"top_station":"Harbin, China","total_7d_cm":0.0},{"region":"southern_hemisphere_ref","display_name":"Southern Hemisphere","station_count":3,"avg_score":3,"max_score":10,"top_station":"Grytviken, South Georgia","total_7d_cm":0.1},{"region":"china_tibetan","display_name":"Tibetan Plateau","station_count":2,"avg_score":2,"max_score":4,"top_station":"Xining, China","total_7d_cm":0.4},{"region":"japan_sea_coast","display_name":"Japan Sea Coast","station_count":3,"avg_score":1,"max_score":2,"top_station":"Toyama, Japan","total_7d_cm":0.2},{"region":"alps_western","display_name":"Western Alps","station_count":3,"avg_score":0,"max_score":1,"top_station":"Zermatt, Switzerland","total_7d_cm":0.0},{"region":"europe_additional","display_name":"Europe Additional","station_count":3,"avg_score":1,"max_score":1,"top_station":"Moscow, Russia","total_7d_cm":0.0},{"region":"alps_eastern","display_name":"Eastern Alps","station_count":2,"avg_score":0,"max_score":0,"top_station":"Innsbruck, Austria","total_7d_cm":0.0},{"region":"south_america","display_name":"South America","station_count":5,"avg_score":0,"max_score":0,"top_station":"Bariloche, Argentina","total_7d_cm":0.0},{"region":"australia_nz","display_name":"Australia & New Zealand","station_count":4,"avg_score":0,"max_score":0,"top_station":"Mount Buller, Australia","total_7d_cm":0.0}],"wisconsin_summary":{"forecast_days":7,"snow_days":4,"max_probability":55,"max_probability_snowfall":"10-30mm (0.5-1.5 inches)","summary_text":"\n7-DAY FORECAST SUMMARY for Northern Wisconsin\nGenerated: March 06, 2026 at 05:32 PM\n\nOVERVIEW:\n  \u2022 4 day(s) with snow potential (\u226530% probability)\n  \u2022 Highest probability: 55% on Monday, 2026-03-09\n  \u2022 Primary patterns: Quiet conditions\n\nDETAILED OUTLOOK:\n\nSaturday, 2026-03-07:\n  \u2601\ufe0f 40% probability - QUIET\n  Expected: 5-20mm (trace-1 inch)\n  Confidence: MODERATE\n\nSunday, 2026-03-08:\n  \u2601\ufe0f 40% probability - QUIET\n  Expected: 5-20mm (trace-1 inch)\n  Confidence: MODERATE\n\nMonday, 2026-03-09:\n  \ud83c\udf28\ufe0f 55% probability - QUIET\n  Expected: 10-30mm (0.5-1.5 inches)\n  Confidence: MODERATE\n\nTuesday, 2026-03-10:\n  \u26aa 25% probability - QUIET\n  Expected: 0-10mm (trace-0.5 inch)\n  Confidence: LOW-MODERATE\n\nWednesday, 2026-03-11:\n  \u26aa 25% probability - QUIET\n  Expected: 0-10mm (trace-0.5 inch)\n  Confidence: LOW-MODERATE\n\nThursday, 2026-03-12:\n  \u26aa 25% probability - QUIET\n  Expected: 0-10mm (trace-0.5 inch)\n  Confidence: LOW-MODERATE\n\nFriday, 2026-03-13:\n  \u2601\ufe0f 40% probability - QUIET\n  Expected: 5-20mm (trace-1 inch)\n  Confidence: MODERATE\n\nALERT LEVELS:\n  \u2744\ufe0f  HIGH (\u226570%) - Major snow likely\n  \ud83c\udf28\ufe0f  MODERATE (50-69%) - Significant snow possible\n  \u2601\ufe0f  LOW (30-49%) - Light snow possible\n  \u26aa MINIMAL (<30%) - Little to no snow expected\n\nLead times:\n  \u2022 Short-range (12-48h): Alberta Clippers, Lake Effect\n  \u2022 Long-range (5-7d): Global atmospheric patterns\n"},"score_distribution":{"high":21,"moderate":58,"low":69}}